media_quality_check/__init__.py
media_quality_check/cli.py
media_quality_check-1.3.0.dist-info/licenses/LICENSE
media_quality_check-1.3.0.dist-info/METADATA
media_quality_check-1.3.0.dist-info/WHEEL
media_quality_check-1.3.0.dist-info/entry_points.txt
media_quality_check-1.3.0.dist-info/top_level.txt
media_quality_check-1.3.0.dist-info/RECORD
